caso/__init__.py
caso/_cmd/__init__.py
caso/_cmd/extract.py
caso/_cmd/projects.py
caso/config.py
caso/exception.py
caso/extract/__init__.py
caso/extract/base.py
caso/extract/manager.py
caso/extract/openstack/__init__.py
caso/extract/openstack/base.py
caso/extract/openstack/cinder.py
caso/extract/openstack/neutron.py
caso/extract/openstack/nova.py
caso/keystone_client.py
caso/loading.py
caso/manager.py
caso/messenger/__init__.py
caso/messenger/logstash.py
caso/messenger/noop.py
caso/messenger/ssm.py
caso/opts.py
caso/record.py
caso/tests/__init__.py
caso/tests/base.py
caso/tests/conftest.py
caso/tests/extract/__init__.py
caso/tests/extract/test_manager.py
caso/tests/extract/test_nova.py
caso/tests/test_cmd_projects.py
caso/tests/test_manager.py
caso/tests/test_record.py
caso/tests/test_ssm.py
caso/utils.py
caso-5.2.0.dist-info/METADATA
caso-5.2.0.dist-info/WHEEL
caso-5.2.0.dist-info/entry_points.txt
caso-5.2.0.dist-info/licenses/LICENSE
caso-5.2.0.dist-info/RECORD
